fastoad_notebooks/.gitignore
fastoad_notebooks/01_tutorial/01_tutorial.ipynb
fastoad_notebooks/01_tutorial/02_postprocessing.ipynb
fastoad_notebooks/01_tutorial/__init__.py
fastoad_notebooks/01_tutorial/data/__init__.py
fastoad_notebooks/01_tutorial/data/CeRAS01_baseline.xml
fastoad_notebooks/01_tutorial/data/oad_process_timestep_mission.yml
fastoad_notebooks/01_tutorial/img/__init__.py
fastoad_notebooks/01_tutorial/img/logo-ISAE_SUPAERO.png
fastoad_notebooks/01_tutorial/img/logo-onera.png
fastoad_notebooks/01_tutorial/img/user_files_arch.svg
fastoad_notebooks/01_tutorial/img/variable_viewer_change_range.gif
fastoad_notebooks/02_CeRAS_case_study/__init__.py
fastoad_notebooks/02_CeRAS_case_study/CeRAS_case_study.ipynb
fastoad_notebooks/02_CeRAS_case_study/ceras_utils.py
fastoad_notebooks/02_CeRAS_case_study/data/__init__.py
fastoad_notebooks/02_CeRAS_case_study/data/CeRAS_data_for_plots.xml
fastoad_notebooks/02_CeRAS_case_study/data/CeRAS_missions.yml
fastoad_notebooks/02_CeRAS_case_study/data/CeRAS_reference_data.xml
fastoad_notebooks/02_CeRAS_case_study/data/CSR-01_missionDesign_R4630_PL17000_out.csv
fastoad_notebooks/02_CeRAS_case_study/data/CSR-01_missionStudy_R5093_PL13608_out.csv
fastoad_notebooks/02_CeRAS_case_study/data/CSR-01_missionStudy_R926_PL13608_out.csv
fastoad_notebooks/02_CeRAS_case_study/data/oad_sizing.yml
fastoad_notebooks/02_CeRAS_case_study/data/oad_sizing_out.xml
fastoad_notebooks/02_CeRAS_case_study/data/operational_missions.yml
fastoad_notebooks/02_CeRAS_case_study/img/__init__.py
fastoad_notebooks/02_CeRAS_case_study/img/logo-ISAE_SUPAERO.png
fastoad_notebooks/02_CeRAS_case_study/img/logo-onera.png
fastoad_notebooks/02_CeRAS_case_study/img/mass_breakdown_1.png
fastoad_notebooks/02_CeRAS_case_study/img/mass_breakdown_2.png
fastoad_notebooks/02_CeRAS_case_study/img/wing_parameters.png
fastoad_notebooks/03_custom_modules/__init__.py
fastoad_notebooks/03_custom_modules/beam_problem.ipynb
fastoad_notebooks/03_custom_modules/data/__init__.py
fast_oad_notebooks-0.2.0.dist-info/LICENSE
fast_oad_notebooks-0.2.0.dist-info/WHEEL
fast_oad_notebooks-0.2.0.dist-info/METADATA
fast_oad_notebooks-0.2.0.dist-info/RECORD
