Metadata-Version: 2.1
Name: fast-oad-notebooks
Version: 0.2.0
Summary: Tutorial notebooks for FAST-OAD
Author: Scott DELBECQ
Author-email: Scott.DELBECQ@isae-supaero.fr
Requires-Python: >=3.7,<4.0
Classifier: Programming Language :: Python :: 3
Classifier: Programming Language :: Python :: 3.7
Classifier: Programming Language :: Python :: 3.8
Classifier: Programming Language :: Python :: 3.9
Requires-Dist: fast-oad (>=1.1.0,<2.0.0)
